ai_project_os_mcp/__init__.py
ai_project_os_mcp/cli.py
ai_project_os_mcp/config.py
ai_project_os_mcp/server.py
ai_project_os_mcp/adapters/__init__.py
ai_project_os_mcp/adapters/claude.py
ai_project_os_mcp/adapters/cursor.py
ai_project_os_mcp/adapters/trae.py
ai_project_os_mcp/core/__init__.py
ai_project_os_mcp/core/accountability_manager.py
ai_project_os_mcp/core/accountability_models.py
ai_project_os_mcp/core/agent_coordination_manager.py
ai_project_os_mcp/core/agent_models.py
ai_project_os_mcp/core/agent_registry.py
ai_project_os_mcp/core/arbitration_models.py
ai_project_os_mcp/core/architecture_linter.py
ai_project_os_mcp/core/auth.py
ai_project_os_mcp/core/decision_models.py
ai_project_os_mcp/core/event_store.py
ai_project_os_mcp/core/events.py
ai_project_os_mcp/core/external_authority_models.py
ai_project_os_mcp/core/external_governance_interface.py
ai_project_os_mcp/core/governance_attestation.py
ai_project_os_mcp/core/governance_disclosure_models.py
ai_project_os_mcp/core/governance_engine.py
ai_project_os_mcp/core/governance_finality_models.py
ai_project_os_mcp/core/governance_lifecycle_models.py
ai_project_os_mcp/core/governance_lifecycle_phase3.py
ai_project_os_mcp/core/governance_proof_manager.py
ai_project_os_mcp/core/governance_proof_models.py
ai_project_os_mcp/core/human_sovereignty_models.py
ai_project_os_mcp/core/jurisdiction_models.py
ai_project_os_mcp/core/policy_engine.py
ai_project_os_mcp/core/regulatory_freeze_manager.py
ai_project_os_mcp/core/rule_engine.py
ai_project_os_mcp/core/score_engine.py
ai_project_os_mcp/core/session_manager.py
ai_project_os_mcp/core/sovereignty_context.py
ai_project_os_mcp/core/stage_manager.py
ai_project_os_mcp/core/stage_models.py
ai_project_os_mcp/core/state_manager.py
ai_project_os_mcp/core/trigger_engine.py
ai_project_os_mcp/core/trust_anchor_manager.py
ai_project_os_mcp/core/trust_anchor_models.py
ai_project_os_mcp/core/violation.py
ai_project_os_mcp/tools/__init__.py
ai_project_os_mcp/tools/audit_security.py
ai_project_os_mcp-2.5.0.dist-info/licenses/LICENSE
ai_project_os_mcp-2.5.0.dist-info/METADATA
ai_project_os_mcp-2.5.0.dist-info/WHEEL
ai_project_os_mcp-2.5.0.dist-info/entry_points.txt
ai_project_os_mcp-2.5.0.dist-info/top_level.txt
ai_project_os_mcp-2.5.0.dist-info/RECORD
