Metadata-Version: 2.4
Name: ai-project-os-mcp
Version: 2.5.0
Summary: Enterprise-grade AI engineering governance MCP server
Author-email: AI Project OS Team <contact@ai-project-os.com>
License: MIT
Project-URL: Homepage, https://github.com/wuxiaolong123121/ai-project-os-mcp
Project-URL: Source, https://github.com/wuxiaolong123121/ai-project-os-mcp
Project-URL: Bug Tracker, https://github.com/wuxiaolong123121/ai-project-os-mcp/issues
Project-URL: Documentation, https://github.com/wuxiaolong123121/ai-project-os-mcp#readme
Keywords: mcp,ai-governance,software-engineering,audit,dependency-guard
Classifier: Development Status :: 5 - Production/Stable
Classifier: Intended Audience :: Developers
Classifier: License :: OSI Approved :: MIT License
Classifier: Programming Language :: Python :: 3
Classifier: Programming Language :: Python :: 3.8
Classifier: Programming Language :: Python :: 3.9
Classifier: Programming Language :: Python :: 3.10
Classifier: Programming Language :: Python :: 3.11
Classifier: Topic :: Software Development :: Code Generators
Classifier: Topic :: Software Development :: Quality Assurance
Requires-Python: >=3.8
License-File: LICENSE
Requires-Dist: fastapi>=0.68.0
Requires-Dist: uvicorn>=0.15.0
Requires-Dist: pydantic>=1.8.0
Requires-Dist: pyyaml>=5.4.0
Provides-Extra: dev
Requires-Dist: pytest>=6.0; extra == "dev"
Requires-Dist: black>=21.0; extra == "dev"
Requires-Dist: isort>=5.0; extra == "dev"
Requires-Dist: build; extra == "dev"
Requires-Dist: twine; extra == "dev"
Dynamic: license-file
